.DS_Store
_C/__init__.cpython-39-darwin.so
_C/_functional.cpython-39-darwin.so
quant/__init__.py
quant/config.py
quant/autoalpha/__init__.py
quant/autoalpha/boost/__init__.py
quant/autoalpha/cnn/__init__.py
quant/autoalpha/gplearn/__init__.py
quant/autoalpha/gplearn/_program.py
quant/autoalpha/gplearn/fitness.py
quant/autoalpha/gplearn/functions.py
quant/autoalpha/gplearn/genetic.py
quant/autoalpha/gplearn/utils.py
quant/edbt/__init__.py
quant/op/CrossSectionalOperators.py
quant/op/__init__.py
quant/op/_func.cpython-39-darwin.so
quant/op/algos.py
quant/op/base.py
quant/op/functional.py
quant/vbt/__init__.py
quant/vbt/backtest.py
quant/vbt/benchmark.py
quant/vbt/dataset.py
quant/vbt/rebalance.py
quant/vbt/stats.py
quant/vbt/universe.py
quant/vbt/utils.py
quant/visualization/__init__.py
quant/visualization/visualization.py
torchqtm/__init__.py
torchqtm/base.py
torchqtm/config.py
torchqtm/configurator.py
torchqtm/constants.py
torchqtm/types.py
torchqtm/utils.py
torchqtm/_C/__init__.cpython-39-darwin.so
torchqtm/_C/__init__.py
torchqtm/_C/_functional.cpython-39-darwin.so
torchqtm/_C/_rolling.cpython-39-darwin.so
torchqtm/_libs/__init__.py
torchqtm/_libs/tslibs/__init__.py
torchqtm/_libs/window/__init__.py
torchqtm/alphas/__init__.py
torchqtm/alphas/alpha101.py
torchqtm/alphas/alphas.py
torchqtm/alphas/chatgpt.py
torchqtm/alphas/introduction.py
torchqtm/alphas/ml.py
torchqtm/alphas/paper.py
torchqtm/alphas/statistical.py
torchqtm/alphas/technical.py
torchqtm/alphas/autoalpha/__init__.py
torchqtm/alphas/autoalpha/boost/__init__.py
torchqtm/alphas/autoalpha/cnn/__init__.py
torchqtm/alphas/autoalpha/gplearn/__init__.py
torchqtm/alphas/autoalpha/gplearn/_program.py
torchqtm/alphas/autoalpha/gplearn/fitness.py
torchqtm/alphas/autoalpha/gplearn/functions.py
torchqtm/alphas/autoalpha/gplearn/genetic.py
torchqtm/alphas/autoalpha/gplearn/utils.py
torchqtm/assets/__init__.py
torchqtm/assets/_assets.py
torchqtm/autoalpha/__init__.py
torchqtm/autoalpha/boost/__init__.py
torchqtm-0.6.0.dist-info/LICENSE
torchqtm-0.6.0.dist-info/METADATA
torchqtm-0.6.0.dist-info/WHEEL
torchqtm-0.6.0.dist-info/top_level.txt
torchqtm-0.6.0.dist-info/RECORD
