Metadata-Version: 2.1
Name: torchqtm
Version: 0.6.0
Summary: None
Home-page: https://github.com/nymath/torchqtm
Download-URL: https://github.com/nymath/torchqtm/releases/tag/
Author: ny
Author-email: nymath@163.com
Classifier: Programming Language :: Python :: 3
Classifier: License :: OSI Approved :: MIT License
Classifier: Operating System :: Unix
Requires-Python: >=3.9
License-File: LICENSE
Requires-Dist: numpy
Requires-Dist: pandas
Requires-Dist: pandas-market-calendars
Requires-Dist: cython
